{"commitInfo":{"timestamp":1765802609435,"operation":"STREAMING UPDATE","operationParameters":{"outputMode":"Append","queryId":"0a377067-2140-4a30-8ec6-53946f56b40c","epochId":"92"},"readVersion":91,"isolationLevel":"Serializable","isBlindAppend":true,"operationMetrics":{"numRemovedFiles":"0","numOutputRows":"2","numOutputBytes":"3249","numAddedFiles":"1"},"engineInfo":"Apache-Spark/3.5.1 Delta-Lake/3.2.0","txnId":"f3c6cabe-0bce-4395-8912-be7527a7189c"}}
{"txn":{"appId":"0a377067-2140-4a30-8ec6-53946f56b40c","version":92,"lastUpdated":1765802609434}}
{"add":{"path":"part-00000-28a688eb-1fb0-4369-9a1f-1b09c6201236-c000.snappy.parquet","partitionValues":{},"size":3249,"modificationTime":1765802609422,"dataChange":true,"stats":"{\"numRecords\":2,\"minValues\":{\"event_id\":\"EVT_4ELZLUO7\",\"order_id\":\"ORD_AHZD3CHY\",\"user_id\":1797,\"region\":\"MENA\",\"channel\":\"store\",\"amount\":293.02,\"currency\":\"GBP\",\"status\":\"PENDING\",\"created_at\":\"2025-12-15T12:43:25.425841+00:00\",\"event_time\":\"2025-12-15T13:43:25.425+01:00\",\"ingest_time\":\"2025-12-15T13:43:26.797+01:00\"},\"maxValues\":{\"event_id\":\"EVT_BF50MLAL\",\"order_id\":\"ORD_FXRPKUF4\",\"user_id\":7139,\"region\":\"US\",\"channel\":\"store\",\"amount\":357.62,\"currency\":\"USD\",\"status\":\"SUCCESS\",\"created_at\":\"2025-12-15T12:43:26.428833+00:00\",\"event_time\":\"2025-12-15T13:43:26.428+01:00\",\"ingest_time\":\"2025-12-15T13:43:26.797+01:00\"},\"nullCount\":{\"event_id\":0,\"order_id\":0,\"user_id\":0,\"region\":0,\"channel\":0,\"amount\":0,\"currency\":0,\"status\":0,\"created_at\":0,\"event_time\":0,\"ingest_time\":0}}"}}
